{
    "name": "Hindent",
    "scopeName": "source.hin",
    "fileTypes": ["hin"],
    "patterns": [
        {
            "name": "comment.block.hindent",
			"begin": "^\\.",
			"end": "\\.$"
		},
        {
            "name": "string.quoted.double.hindent",
            "begin": "\"",
            "end": "\"",
            "patterns": [
                {
                    "name": "constant.character.escape.hindent",
                    "match": "\\\\."
                }
            ]
        },
        {
            "name": "constant.numeric.hindent",
            "match": "\\b[0-9]+\\b"
        },
        {
            "name": "comment.line.hindent",
            "match": ";.*$"
        },
        {
            "name": "variable.hindent",
            "match": ".+"
        }
    ],
    "repository": {
        "code": {
            "patterns": [
            ]
        }
    }
}
